COPYING
LICENSE
MANIFEST.in
README.rst
setup.py
django_queryset_csv.egg-info/PKG-INFO
django_queryset_csv.egg-info/SOURCES.txt
django_queryset_csv.egg-info/dependency_links.txt
django_queryset_csv.egg-info/requires.txt
django_queryset_csv.egg-info/top_level.txt
djqscsv/__init__.py
djqscsv/_csql.py
djqscsv/djqscsv.py