Metadata-Version: 1.1
Name: django-queryset-csv
Version: 0.3.3
Summary: A simple python module for writing querysets to csv
Home-page: http://github.com/azavea/django-queryset-csv
Author: Steve Lamb
Author-email: slamb@azavea.com
License: UNKNOWN
Keywords: django queryset csv
Platform: UNKNOWN
Classifier: Development Status :: 4 - Beta
Classifier: Intended Audience :: Developers
Classifier: Programming Language :: Python
Classifier: Environment :: Plugins
Classifier: Framework :: Django
Classifier: License :: OSI Approved :: GNU General Public License (GPL)
